sharkpy/__init__.py
sharkpy/battle.py
sharkpy/core.py
sharkpy/explaining.py
sharkpy/learning.py
sharkpy/plotting.py
sharkpy/predicting.py
sharkpy/reporting.py
sharkpy/saving.py
sharkpy/shapash_integration.py
sharkpy-1.0.1.dist-info/METADATA
sharkpy-1.0.1.dist-info/WHEEL
sharkpy-1.0.1.dist-info/licenses/LICENSE
sharkpy-1.0.1.dist-info/RECORD
