Metadata-Version: 2.4
Name: sharkpy
Version: 1.0.1
Summary: A friendly machine learning framework with shark-themed feedback 🦈
Project-URL: Homepage, https://github.com/Ezzio11/sharkpy
Project-URL: Documentation, https://sharkpy.readthedocs.io/
Project-URL: Repository, https://github.com/Ezzio11/sharkpy.git
Project-URL: Issues, https://github.com/Ezzio11/sharkpy/issues
Project-URL: Changelog, https://github.com/Ezzio11/sharkpy/blob/main/CHANGELOG.md
Author-email: Ezz Eldin Ahmed <ezzeldinahmad96@gmail.com>
Maintainer-email: Ezz Eldin Ahmed <ezzeldinahmad96@gmail.com>
License-File: LICENSE
Keywords: automated ml,data science,education,machine learning,model comparison,reporting,visualization
Classifier: Development Status :: 4 - Beta
Classifier: Intended Audience :: Education
Classifier: Intended Audience :: Science/Research
Classifier: License :: OSI Approved :: MIT License
Classifier: Programming Language :: Python :: 3
Classifier: Programming Language :: Python :: 3.8
Classifier: Programming Language :: Python :: 3.9
Classifier: Programming Language :: Python :: 3.10
Classifier: Programming Language :: Python :: 3.11
Classifier: Programming Language :: Python :: 3.12
Classifier: Programming Language :: Python :: 3.13
Classifier: Topic :: Education
Classifier: Topic :: Scientific/Engineering :: Artificial Intelligence
Classifier: Topic :: Software Development :: Libraries :: Python Modules
Requires-Python: >=3.8
Requires-Dist: docx2pdf>=0.1.8
Requires-Dist: joblib>=1.2.0
Requires-Dist: matplotlib>=3.6.0
Requires-Dist: numpy>=2.1.0
Requires-Dist: optuna>=3.0.0
Requires-Dist: pandas>=2.2.3
Requires-Dist: python-docx>=0.8.11
Requires-Dist: scikit-learn>=1.2.0
Requires-Dist: seaborn>=0.12.0
Requires-Dist: shapash>=2.3.0
Requires-Dist: statsmodels>=0.13.0
Requires-Dist: xgboost>=1.7.0
Provides-Extra: dev
Requires-Dist: black>=21.5b2; extra == 'dev'
Requires-Dist: flake8>=3.9.0; extra == 'dev'
Requires-Dist: pytest-cov>=2.12.0; extra == 'dev'
Requires-Dist: pytest>=6.0.0; extra == 'dev'
Provides-Extra: docs
Requires-Dist: sphinx-rtd-theme>=0.5.0; extra == 'docs'
Requires-Dist: sphinx>=4.0.0; extra == 'docs'
Provides-Extra: full
Requires-Dist: catboost>=1.2; extra == 'full'
Requires-Dist: lightgbm>=3.3.2; extra == 'full'
